{
    "FixedFileInfo": {
        "FileVersion": {
            "Major": 1,
            "Minor": 2,
            "Patch": 0,
            "Build": 0
        },
        "ProductVersion": {
            "Major": 1,
            "Minor": 2,
            "Patch": 0,
            "Build": 0
        },
        "FileFlagsMask": "3f",
        "FileFlags": "00",
        "FileOS": "040004",
        "FileType": "01",
        "FileSubType": "00"
    },
    "StringFileInfo": {
        "Comments": "Anti Keyboard Chattering - An open-source tool to mitigate unintended key presses.",
        "CompanyName": "RedrootDEV (https://github.com/RedrootDEV)",
        "FileDescription": "AKC - Anti Keyboard Chattering",
        "FileVersion": "1.2.0.0",
        "InternalName": "AKC",
        "LegalCopyright": "© 2024 RedrootDEV. Licensed under the MIT License.",
        "LegalTrademarks": "Documentation and license available at https://github.com/RedrootDEV/AKC-Anti-Keyboard-Chattering",
        "OriginalFilename": "AKC.exe",
        "PrivateBuild": "This is a public release. Contributions welcome at GitHub.",
        "ProductName": "AKC - Anti Keyboard Chattering",
        "ProductVersion": "1.2.0.0",
        "SpecialBuild": "Standard build without additional modifications."
    },
    "VarFileInfo": {
        "Translation": {
            "LangID": "0409",
            "CharsetID": "04B0"
        }
    },
    "IconPath": "icon.ico",
    "ManifestPath": ""
}
